[{"Date":"28-11-2020","RollingCorrelations":0.8886488679},{"Date":"29-11-2020","RollingCorrelations":0.8840493598},{"Date":"30-11-2020","RollingCorrelations":0.9055415172},{"Date":"01-12-2020","RollingCorrelations":0.9007090979},{"Date":"02-12-2020","RollingCorrelations":0.8972708016},{"Date":"03-12-2020","RollingCorrelations":0.8883271133},{"Date":"04-12-2020","RollingCorrelations":0.9009054579},{"Date":"05-12-2020","RollingCorrelations":0.8870897019},{"Date":"06-12-2020","RollingCorrelations":0.8916781976},{"Date":"07-12-2020","RollingCorrelations":0.8778044334},{"Date":"08-12-2020","RollingCorrelations":0.8904621306},{"Date":"09-12-2020","RollingCorrelations":0.8903919979},{"Date":"10-12-2020","RollingCorrelations":0.8275195199},{"Date":"11-12-2020","RollingCorrelations":0.8037319875},{"Date":"12-12-2020","RollingCorrelations":0.8174008059},{"Date":"13-12-2020","RollingCorrelations":0.8133276538},{"Date":"14-12-2020","RollingCorrelations":0.8173950376},{"Date":"15-12-2020","RollingCorrelations":0.819069687},{"Date":"16-12-2020","RollingCorrelations":0.7661185307},{"Date":"17-12-2020","RollingCorrelations":0.7660238963},{"Date":"18-12-2020","RollingCorrelations":0.6896139125},{"Date":"19-12-2020","RollingCorrelations":0.6820665159},{"Date":"20-12-2020","RollingCorrelations":0.6695481629},{"Date":"21-12-2020","RollingCorrelations":0.7105596422},{"Date":"22-12-2020","RollingCorrelations":0.5951821096},{"Date":"23-12-2020","RollingCorrelations":0.5656734626},{"Date":"24-12-2020","RollingCorrelations":0.650418579},{"Date":"25-12-2020","RollingCorrelations":0.6091620201},{"Date":"26-12-2020","RollingCorrelations":0.5994218005},{"Date":"27-12-2020","RollingCorrelations":0.5933533184},{"Date":"28-12-2020","RollingCorrelations":0.6263926127},{"Date":"29-12-2020","RollingCorrelations":0.6388597241},{"Date":"30-12-2020","RollingCorrelations":0.6200849251},{"Date":"31-12-2020","RollingCorrelations":0.5686195304},{"Date":"01-01-2021","RollingCorrelations":0.4407111358},{"Date":"02-01-2021","RollingCorrelations":0.4020104976},{"Date":"03-01-2021","RollingCorrelations":0.372200598},{"Date":"04-01-2021","RollingCorrelations":0.3282615149},{"Date":"05-01-2021","RollingCorrelations":0.0565020454},{"Date":"06-01-2021","RollingCorrelations":-0.1419182212},{"Date":"07-01-2021","RollingCorrelations":-0.2480692879},{"Date":"08-01-2021","RollingCorrelations":-0.2471533508},{"Date":"09-01-2021","RollingCorrelations":0.0034487374},{"Date":"10-01-2021","RollingCorrelations":0.1240327711},{"Date":"11-01-2021","RollingCorrelations":0.2179874551},{"Date":"12-01-2021","RollingCorrelations":0.1478553859},{"Date":"13-01-2021","RollingCorrelations":0.1271938882},{"Date":"14-01-2021","RollingCorrelations":0.1240586712},{"Date":"15-01-2021","RollingCorrelations":0.1390733761},{"Date":"16-01-2021","RollingCorrelations":0.139317694},{"Date":"17-01-2021","RollingCorrelations":0.2386452963},{"Date":"18-01-2021","RollingCorrelations":0.1922039325},{"Date":"19-01-2021","RollingCorrelations":0.3185251432},{"Date":"20-01-2021","RollingCorrelations":0.3264546847},{"Date":"21-01-2021","RollingCorrelations":0.4548135712},{"Date":"22-01-2021","RollingCorrelations":0.5279151374},{"Date":"23-01-2021","RollingCorrelations":0.3928687727},{"Date":"24-01-2021","RollingCorrelations":0.3204027391},{"Date":"25-01-2021","RollingCorrelations":0.3103219491},{"Date":"26-01-2021","RollingCorrelations":0.3817971614},{"Date":"27-01-2021","RollingCorrelations":0.4104635611},{"Date":"28-01-2021","RollingCorrelations":0.4399618404},{"Date":"29-01-2021","RollingCorrelations":0.2555693176},{"Date":"30-01-2021","RollingCorrelations":0.3545971785},{"Date":"31-01-2021","RollingCorrelations":0.2668734567},{"Date":"01-02-2021","RollingCorrelations":0.292192814},{"Date":"02-02-2021","RollingCorrelations":0.2551125554},{"Date":"03-02-2021","RollingCorrelations":0.3130123631},{"Date":"04-02-2021","RollingCorrelations":0.0319378155},{"Date":"05-02-2021","RollingCorrelations":0.223588414},{"Date":"06-02-2021","RollingCorrelations":0.2394121632},{"Date":"07-02-2021","RollingCorrelations":0.2294848373},{"Date":"08-02-2021","RollingCorrelations":0.3772291544},{"Date":"09-02-2021","RollingCorrelations":0.2928121039},{"Date":"10-02-2021","RollingCorrelations":-0.0244218822},{"Date":"11-02-2021","RollingCorrelations":-0.2774694519},{"Date":"12-02-2021","RollingCorrelations":-0.1917466486},{"Date":"13-02-2021","RollingCorrelations":-0.2623168486},{"Date":"14-02-2021","RollingCorrelations":-0.0976624012},{"Date":"15-02-2021","RollingCorrelations":-0.0347201773},{"Date":"16-02-2021","RollingCorrelations":-0.0382103733},{"Date":"17-02-2021","RollingCorrelations":-0.033446072},{"Date":"18-02-2021","RollingCorrelations":-0.0429914784},{"Date":"19-02-2021","RollingCorrelations":-0.1036336807},{"Date":"20-02-2021","RollingCorrelations":-0.0681246693},{"Date":"21-02-2021","RollingCorrelations":-0.0557824382},{"Date":"22-02-2021","RollingCorrelations":-0.0739212664},{"Date":"23-02-2021","RollingCorrelations":0.0498894476},{"Date":"24-02-2021","RollingCorrelations":0.1595070123},{"Date":"25-02-2021","RollingCorrelations":0.5393769045},{"Date":"26-02-2021","RollingCorrelations":0.5707282059},{"Date":"27-02-2021","RollingCorrelations":0.6990620288},{"Date":"28-02-2021","RollingCorrelations":0.6790426102},{"Date":"01-03-2021","RollingCorrelations":0.7138577478},{"Date":"02-03-2021","RollingCorrelations":0.7292359935},{"Date":"03-03-2021","RollingCorrelations":0.7297554451},{"Date":"04-03-2021","RollingCorrelations":0.6987022518},{"Date":"05-03-2021","RollingCorrelations":0.8077527556},{"Date":"06-03-2021","RollingCorrelations":0.798629079},{"Date":"07-03-2021","RollingCorrelations":0.7976299391},{"Date":"08-03-2021","RollingCorrelations":0.7572227165},{"Date":"09-03-2021","RollingCorrelations":0.4163512989},{"Date":"10-03-2021","RollingCorrelations":0.4519372389},{"Date":"11-03-2021","RollingCorrelations":0.3541136018},{"Date":"12-03-2021","RollingCorrelations":0.405524196},{"Date":"13-03-2021","RollingCorrelations":0.468353542},{"Date":"14-03-2021","RollingCorrelations":0.4645565512},{"Date":"15-03-2021","RollingCorrelations":0.3953554565},{"Date":"16-03-2021","RollingCorrelations":0.4315441266},{"Date":"17-03-2021","RollingCorrelations":0.407360258},{"Date":"18-03-2021","RollingCorrelations":0.490981947},{"Date":"19-03-2021","RollingCorrelations":0.5058155858},{"Date":"20-03-2021","RollingCorrelations":0.4196195413},{"Date":"21-03-2021","RollingCorrelations":0.3780112604},{"Date":"22-03-2021","RollingCorrelations":0.4641459921},{"Date":"23-03-2021","RollingCorrelations":0.6469177006},{"Date":"24-03-2021","RollingCorrelations":0.6516935019},{"Date":"25-03-2021","RollingCorrelations":0.6597620776},{"Date":"26-03-2021","RollingCorrelations":0.6466145861},{"Date":"27-03-2021","RollingCorrelations":0.6341122642},{"Date":"28-03-2021","RollingCorrelations":0.5943995571},{"Date":"29-03-2021","RollingCorrelations":0.5968112234},{"Date":"30-03-2021","RollingCorrelations":0.6539953474},{"Date":"31-03-2021","RollingCorrelations":0.2844869721},{"Date":"01-04-2021","RollingCorrelations":0.3004396515},{"Date":"02-04-2021","RollingCorrelations":0.2737382274},{"Date":"03-04-2021","RollingCorrelations":0.2846722369},{"Date":"04-04-2021","RollingCorrelations":0.3645132001},{"Date":"05-04-2021","RollingCorrelations":0.2458756519},{"Date":"06-04-2021","RollingCorrelations":0.1960606509},{"Date":"07-04-2021","RollingCorrelations":0.251267352},{"Date":"08-04-2021","RollingCorrelations":0.262595935},{"Date":"09-04-2021","RollingCorrelations":0.1423313786},{"Date":"10-04-2021","RollingCorrelations":0.1136167032},{"Date":"11-04-2021","RollingCorrelations":0.1619760338},{"Date":"12-04-2021","RollingCorrelations":0.1603147401},{"Date":"13-04-2021","RollingCorrelations":0.1374219211},{"Date":"14-04-2021","RollingCorrelations":0.1913909297},{"Date":"15-04-2021","RollingCorrelations":0.0359502116},{"Date":"16-04-2021","RollingCorrelations":0.0793426496},{"Date":"17-04-2021","RollingCorrelations":0.1634901539},{"Date":"18-04-2021","RollingCorrelations":0.298957512},{"Date":"19-04-2021","RollingCorrelations":0.3455499853},{"Date":"20-04-2021","RollingCorrelations":0.3903631696},{"Date":"21-04-2021","RollingCorrelations":0.3676503369},{"Date":"22-04-2021","RollingCorrelations":0.3735907262},{"Date":"23-04-2021","RollingCorrelations":0.4148150664},{"Date":"24-04-2021","RollingCorrelations":0.4191269072},{"Date":"25-04-2021","RollingCorrelations":0.4247410044},{"Date":"26-04-2021","RollingCorrelations":0.5711994908},{"Date":"27-04-2021","RollingCorrelations":0.6332456004},{"Date":"28-04-2021","RollingCorrelations":0.7429325052},{"Date":"29-04-2021","RollingCorrelations":0.9373245408},{"Date":"30-04-2021","RollingCorrelations":0.946450367},{"Date":"01-05-2021","RollingCorrelations":0.9424399119},{"Date":"02-05-2021","RollingCorrelations":0.9436844969},{"Date":"03-05-2021","RollingCorrelations":0.9084227397},{"Date":"04-05-2021","RollingCorrelations":0.9144825614},{"Date":"05-05-2021","RollingCorrelations":0.8862105319},{"Date":"06-05-2021","RollingCorrelations":0.8828070956},{"Date":"07-05-2021","RollingCorrelations":0.8800556865},{"Date":"08-05-2021","RollingCorrelations":0.866463994},{"Date":"09-05-2021","RollingCorrelations":0.8646956959},{"Date":"10-05-2021","RollingCorrelations":0.8609728906},{"Date":"11-05-2021","RollingCorrelations":0.8584051897},{"Date":"12-05-2021","RollingCorrelations":0.8878710711},{"Date":"13-05-2021","RollingCorrelations":0.8826708081},{"Date":"14-05-2021","RollingCorrelations":0.8791542871},{"Date":"15-05-2021","RollingCorrelations":0.8779253594},{"Date":"16-05-2021","RollingCorrelations":0.866356092},{"Date":"17-05-2021","RollingCorrelations":0.8921739533},{"Date":"18-05-2021","RollingCorrelations":0.8959830784},{"Date":"19-05-2021","RollingCorrelations":0.971478828},{"Date":"20-05-2021","RollingCorrelations":0.9579593618},{"Date":"21-05-2021","RollingCorrelations":0.9603636434},{"Date":"22-05-2021","RollingCorrelations":0.9401610166},{"Date":"23-05-2021","RollingCorrelations":0.9422809179},{"Date":"24-05-2021","RollingCorrelations":0.9529744754},{"Date":"25-05-2021","RollingCorrelations":0.953869479},{"Date":"26-05-2021","RollingCorrelations":0.9558699324},{"Date":"27-05-2021","RollingCorrelations":0.9596089239},{"Date":"28-05-2021","RollingCorrelations":0.9607766502},{"Date":"29-05-2021","RollingCorrelations":0.9605169802},{"Date":"30-05-2021","RollingCorrelations":0.9703215898},{"Date":"31-05-2021","RollingCorrelations":0.9700891544},{"Date":"01-06-2021","RollingCorrelations":0.97635943},{"Date":"02-06-2021","RollingCorrelations":0.9477612668},{"Date":"03-06-2021","RollingCorrelations":0.9507618586},{"Date":"04-06-2021","RollingCorrelations":0.9482172626},{"Date":"05-06-2021","RollingCorrelations":0.9756527741},{"Date":"06-06-2021","RollingCorrelations":0.9739571584},{"Date":"07-06-2021","RollingCorrelations":0.9668995712},{"Date":"08-06-2021","RollingCorrelations":0.9496118551},{"Date":"09-06-2021","RollingCorrelations":0.9465579963},{"Date":"10-06-2021","RollingCorrelations":0.9440342797},{"Date":"11-06-2021","RollingCorrelations":0.9294257138},{"Date":"12-06-2021","RollingCorrelations":0.9264814489},{"Date":"13-06-2021","RollingCorrelations":0.9380335734},{"Date":"14-06-2021","RollingCorrelations":0.9256347162},{"Date":"15-06-2021","RollingCorrelations":0.9243056154},{"Date":"16-06-2021","RollingCorrelations":0.9276131353},{"Date":"17-06-2021","RollingCorrelations":0.9163971054},{"Date":"18-06-2021","RollingCorrelations":0.913853968},{"Date":"19-06-2021","RollingCorrelations":0.9134897596},{"Date":"20-06-2021","RollingCorrelations":0.878331885},{"Date":"21-06-2021","RollingCorrelations":0.9235500758},{"Date":"22-06-2021","RollingCorrelations":0.9450620968},{"Date":"23-06-2021","RollingCorrelations":0.9427083311},{"Date":"24-06-2021","RollingCorrelations":0.8683510902},{"Date":"25-06-2021","RollingCorrelations":0.8659278766},{"Date":"26-06-2021","RollingCorrelations":0.8732487506},{"Date":"27-06-2021","RollingCorrelations":0.8756807325},{"Date":"28-06-2021","RollingCorrelations":0.8688905593},{"Date":"29-06-2021","RollingCorrelations":0.8707758761},{"Date":"30-06-2021","RollingCorrelations":0.8677489718},{"Date":"01-07-2021","RollingCorrelations":0.8632798897},{"Date":"02-07-2021","RollingCorrelations":0.8589472075},{"Date":"03-07-2021","RollingCorrelations":0.8515954722},{"Date":"04-07-2021","RollingCorrelations":0.8432425299},{"Date":"05-07-2021","RollingCorrelations":0.6540464828},{"Date":"06-07-2021","RollingCorrelations":0.5229807095},{"Date":"07-07-2021","RollingCorrelations":0.4942743833},{"Date":"08-07-2021","RollingCorrelations":0.8092388834},{"Date":"09-07-2021","RollingCorrelations":0.7316659816},{"Date":"10-07-2021","RollingCorrelations":0.7546303419},{"Date":"11-07-2021","RollingCorrelations":0.7359468879},{"Date":"12-07-2021","RollingCorrelations":0.7373451627},{"Date":"13-07-2021","RollingCorrelations":0.7260838361},{"Date":"14-07-2021","RollingCorrelations":0.70190262},{"Date":"15-07-2021","RollingCorrelations":0.6728710079},{"Date":"16-07-2021","RollingCorrelations":0.7805477367},{"Date":"17-07-2021","RollingCorrelations":0.7610590315},{"Date":"18-07-2021","RollingCorrelations":0.7188835549},{"Date":"19-07-2021","RollingCorrelations":0.7503827082},{"Date":"20-07-2021","RollingCorrelations":0.8733414433},{"Date":"21-07-2021","RollingCorrelations":0.9286221937},{"Date":"22-07-2021","RollingCorrelations":0.9289981811},{"Date":"23-07-2021","RollingCorrelations":0.9298260372},{"Date":"24-07-2021","RollingCorrelations":0.9371125238},{"Date":"25-07-2021","RollingCorrelations":0.9510785519},{"Date":"26-07-2021","RollingCorrelations":0.9527956906},{"Date":"27-07-2021","RollingCorrelations":0.9543591065},{"Date":"28-07-2021","RollingCorrelations":0.9550095382},{"Date":"29-07-2021","RollingCorrelations":0.9468252425},{"Date":"30-07-2021","RollingCorrelations":0.932985954},{"Date":"31-07-2021","RollingCorrelations":0.9154651604},{"Date":"01-08-2021","RollingCorrelations":0.8968136294},{"Date":"02-08-2021","RollingCorrelations":0.8561712596},{"Date":"03-08-2021","RollingCorrelations":0.8426295499},{"Date":"04-08-2021","RollingCorrelations":0.8697675391},{"Date":"05-08-2021","RollingCorrelations":0.7818111882},{"Date":"06-08-2021","RollingCorrelations":0.7757026111},{"Date":"07-08-2021","RollingCorrelations":0.8174160752},{"Date":"08-08-2021","RollingCorrelations":0.8651500783},{"Date":"09-08-2021","RollingCorrelations":0.8452059107},{"Date":"10-08-2021","RollingCorrelations":0.8454284581},{"Date":"11-08-2021","RollingCorrelations":0.5895390333},{"Date":"12-08-2021","RollingCorrelations":0.5954899592},{"Date":"13-08-2021","RollingCorrelations":0.6366708734},{"Date":"14-08-2021","RollingCorrelations":0.6412709117},{"Date":"15-08-2021","RollingCorrelations":0.5716342182},{"Date":"16-08-2021","RollingCorrelations":0.5327201942},{"Date":"17-08-2021","RollingCorrelations":-0.0449254879},{"Date":"18-08-2021","RollingCorrelations":-0.1569222893},{"Date":"19-08-2021","RollingCorrelations":-0.1510169943},{"Date":"20-08-2021","RollingCorrelations":-0.0941414877},{"Date":"21-08-2021","RollingCorrelations":-0.1203655852},{"Date":"22-08-2021","RollingCorrelations":-0.2769814311},{"Date":"23-08-2021","RollingCorrelations":-0.2846752391},{"Date":"24-08-2021","RollingCorrelations":-0.3778778494},{"Date":"25-08-2021","RollingCorrelations":-0.3885157439},{"Date":"26-08-2021","RollingCorrelations":-0.1875051633},{"Date":"27-08-2021","RollingCorrelations":-0.085937045},{"Date":"28-08-2021","RollingCorrelations":-0.0489188706},{"Date":"29-08-2021","RollingCorrelations":-0.0566718787},{"Date":"30-08-2021","RollingCorrelations":-0.0029461183},{"Date":"31-08-2021","RollingCorrelations":0.0831282573},{"Date":"01-09-2021","RollingCorrelations":0.1436449964},{"Date":"02-09-2021","RollingCorrelations":0.2015693149},{"Date":"03-09-2021","RollingCorrelations":0.1532247164},{"Date":"04-09-2021","RollingCorrelations":0.231565091},{"Date":"05-09-2021","RollingCorrelations":0.2330761282},{"Date":"06-09-2021","RollingCorrelations":0.2344829121},{"Date":"07-09-2021","RollingCorrelations":0.7015961347},{"Date":"08-09-2021","RollingCorrelations":0.7833128386},{"Date":"09-09-2021","RollingCorrelations":0.736441337},{"Date":"10-09-2021","RollingCorrelations":0.5768976268},{"Date":"11-09-2021","RollingCorrelations":0.5956604348},{"Date":"12-09-2021","RollingCorrelations":0.5346325117},{"Date":"13-09-2021","RollingCorrelations":0.5686128347},{"Date":"14-09-2021","RollingCorrelations":0.5064720531},{"Date":"15-09-2021","RollingCorrelations":0.4886696938},{"Date":"16-09-2021","RollingCorrelations":0.3827091052},{"Date":"17-09-2021","RollingCorrelations":0.3702977905},{"Date":"18-09-2021","RollingCorrelations":0.3668018637},{"Date":"19-09-2021","RollingCorrelations":0.3708913373},{"Date":"20-09-2021","RollingCorrelations":0.4789871934},{"Date":"21-09-2021","RollingCorrelations":0.2602152202},{"Date":"22-09-2021","RollingCorrelations":0.4195699434},{"Date":"23-09-2021","RollingCorrelations":0.4226894639},{"Date":"24-09-2021","RollingCorrelations":0.5127464291},{"Date":"25-09-2021","RollingCorrelations":0.4941671594},{"Date":"26-09-2021","RollingCorrelations":0.562033619},{"Date":"27-09-2021","RollingCorrelations":0.5324205951},{"Date":"28-09-2021","RollingCorrelations":0.7223255258},{"Date":"29-09-2021","RollingCorrelations":0.7095407829},{"Date":"30-09-2021","RollingCorrelations":0.8059772921},{"Date":"01-10-2021","RollingCorrelations":0.8813125458},{"Date":"02-10-2021","RollingCorrelations":0.8830336551},{"Date":"03-10-2021","RollingCorrelations":0.8817144796},{"Date":"04-10-2021","RollingCorrelations":0.8041059106},{"Date":"05-10-2021","RollingCorrelations":0.8328008651},{"Date":"06-10-2021","RollingCorrelations":0.642123871},{"Date":"07-10-2021","RollingCorrelations":0.6395299471},{"Date":"08-10-2021","RollingCorrelations":0.604831055},{"Date":"09-10-2021","RollingCorrelations":0.5559973958},{"Date":"10-10-2021","RollingCorrelations":0.6449696688},{"Date":"11-10-2021","RollingCorrelations":0.6763949379},{"Date":"12-10-2021","RollingCorrelations":0.6052864931},{"Date":"13-10-2021","RollingCorrelations":0.6081241152},{"Date":"14-10-2021","RollingCorrelations":0.5114881859},{"Date":"15-10-2021","RollingCorrelations":0.485924257},{"Date":"16-10-2021","RollingCorrelations":0.5457475775},{"Date":"17-10-2021","RollingCorrelations":0.5442744129},{"Date":"18-10-2021","RollingCorrelations":0.5096062034},{"Date":"19-10-2021","RollingCorrelations":0.5593456754},{"Date":"20-10-2021","RollingCorrelations":0.6257389365},{"Date":"21-10-2021","RollingCorrelations":0.4607303288},{"Date":"22-10-2021","RollingCorrelations":0.4458998821},{"Date":"23-10-2021","RollingCorrelations":0.5497100557},{"Date":"24-10-2021","RollingCorrelations":0.293175743},{"Date":"25-10-2021","RollingCorrelations":0.3310916086},{"Date":"26-10-2021","RollingCorrelations":0.2424261552},{"Date":"27-10-2021","RollingCorrelations":0.7465565773},{"Date":"28-10-2021","RollingCorrelations":0.7579165861},{"Date":"29-10-2021","RollingCorrelations":0.7223282597},{"Date":"30-10-2021","RollingCorrelations":0.6672384792},{"Date":"31-10-2021","RollingCorrelations":0.6729561929},{"Date":"01-11-2021","RollingCorrelations":0.6693476845},{"Date":"02-11-2021","RollingCorrelations":0.6631756621},{"Date":"03-11-2021","RollingCorrelations":0.512649049},{"Date":"04-11-2021","RollingCorrelations":0.5013287115},{"Date":"05-11-2021","RollingCorrelations":0.4803448115},{"Date":"06-11-2021","RollingCorrelations":0.4525869715},{"Date":"07-11-2021","RollingCorrelations":0.4482661182},{"Date":"08-11-2021","RollingCorrelations":0.45081376},{"Date":"09-11-2021","RollingCorrelations":0.3886877601},{"Date":"10-11-2021","RollingCorrelations":0.0968901913},{"Date":"11-11-2021","RollingCorrelations":0.067300472},{"Date":"12-11-2021","RollingCorrelations":0.1380736944},{"Date":"13-11-2021","RollingCorrelations":0.2900459668},{"Date":"14-11-2021","RollingCorrelations":0.2276995568},{"Date":"15-11-2021","RollingCorrelations":0.139449052},{"Date":"16-11-2021","RollingCorrelations":0.0258168322},{"Date":"17-11-2021","RollingCorrelations":0.0849933119},{"Date":"18-11-2021","RollingCorrelations":0.2791783467},{"Date":"19-11-2021","RollingCorrelations":0.3446602021},{"Date":"20-11-2021","RollingCorrelations":0.3480411753},{"Date":"21-11-2021","RollingCorrelations":0.336027872},{"Date":"22-11-2021","RollingCorrelations":0.3094113794},{"Date":"23-11-2021","RollingCorrelations":0.3112726715},{"Date":"24-11-2021","RollingCorrelations":0.2674789596},{"Date":"25-11-2021","RollingCorrelations":0.2664082458},{"Date":"26-11-2021","RollingCorrelations":0.3838099341},{"Date":"27-11-2021","RollingCorrelations":0.3331850165},{"Date":"28-11-2021","RollingCorrelations":0.3483047589},{"Date":"29-11-2021","RollingCorrelations":0.4495438182},{"Date":"30-11-2021","RollingCorrelations":0.6365380732},{"Date":"01-12-2021","RollingCorrelations":0.6130305584},{"Date":"02-12-2021","RollingCorrelations":0.5208494965},{"Date":"03-12-2021","RollingCorrelations":0.4172013647},{"Date":"04-12-2021","RollingCorrelations":0.5432841957},{"Date":"05-12-2021","RollingCorrelations":0.5353496508},{"Date":"06-12-2021","RollingCorrelations":0.7144290341},{"Date":"07-12-2021","RollingCorrelations":0.7138123935},{"Date":"08-12-2021","RollingCorrelations":0.726899144},{"Date":"09-12-2021","RollingCorrelations":0.7698169643},{"Date":"10-12-2021","RollingCorrelations":0.6998080376},{"Date":"11-12-2021","RollingCorrelations":0.7366296184},{"Date":"12-12-2021","RollingCorrelations":0.73914988},{"Date":"13-12-2021","RollingCorrelations":0.7715911495},{"Date":"14-12-2021","RollingCorrelations":0.7381091297},{"Date":"15-12-2021","RollingCorrelations":0.7333954741},{"Date":"16-12-2021","RollingCorrelations":0.8003342622},{"Date":"17-12-2021","RollingCorrelations":0.5544660505},{"Date":"18-12-2021","RollingCorrelations":0.4369966497},{"Date":"19-12-2021","RollingCorrelations":0.399964156},{"Date":"20-12-2021","RollingCorrelations":0.3265481618},{"Date":"21-12-2021","RollingCorrelations":0.4467823316},{"Date":"22-12-2021","RollingCorrelations":0.4043057061},{"Date":"23-12-2021","RollingCorrelations":0.3375051337},{"Date":"24-12-2021","RollingCorrelations":0.3616493273},{"Date":"25-12-2021","RollingCorrelations":0.3161945283},{"Date":"26-12-2021","RollingCorrelations":0.3095783978},{"Date":"27-12-2021","RollingCorrelations":0.075228415},{"Date":"28-12-2021","RollingCorrelations":0.1577758961},{"Date":"29-12-2021","RollingCorrelations":-0.0075751234},{"Date":"30-12-2021","RollingCorrelations":-0.045921806},{"Date":"31-12-2021","RollingCorrelations":0.3021172602},{"Date":"01-01-2022","RollingCorrelations":0.3160802526},{"Date":"02-01-2022","RollingCorrelations":0.2836233118},{"Date":"03-01-2022","RollingCorrelations":0.4123627381},{"Date":"04-01-2022","RollingCorrelations":0.3707233407},{"Date":"05-01-2022","RollingCorrelations":0.4914064307},{"Date":"06-01-2022","RollingCorrelations":0.3681635454},{"Date":"07-01-2022","RollingCorrelations":0.4563742028},{"Date":"08-01-2022","RollingCorrelations":0.4426821038},{"Date":"09-01-2022","RollingCorrelations":0.4826883386},{"Date":"10-01-2022","RollingCorrelations":0.507922279},{"Date":"11-01-2022","RollingCorrelations":0.5467812729},{"Date":"12-01-2022","RollingCorrelations":0.6391257605},{"Date":"13-01-2022","RollingCorrelations":0.6717908487},{"Date":"14-01-2022","RollingCorrelations":0.8337111527},{"Date":"15-01-2022","RollingCorrelations":0.8326846744},{"Date":"16-01-2022","RollingCorrelations":0.8237719144},{"Date":"17-01-2022","RollingCorrelations":0.7529257269},{"Date":"18-01-2022","RollingCorrelations":0.7313910853},{"Date":"19-01-2022","RollingCorrelations":0.7013661274},{"Date":"20-01-2022","RollingCorrelations":0.7133116288},{"Date":"21-01-2022","RollingCorrelations":0.8320589744},{"Date":"22-01-2022","RollingCorrelations":0.8550665202},{"Date":"23-01-2022","RollingCorrelations":0.8528248624},{"Date":"24-01-2022","RollingCorrelations":0.835688225},{"Date":"25-01-2022","RollingCorrelations":0.8211428644},{"Date":"26-01-2022","RollingCorrelations":0.7835102512},{"Date":"27-01-2022","RollingCorrelations":0.7798362209},{"Date":"28-01-2022","RollingCorrelations":0.7887010365},{"Date":"29-01-2022","RollingCorrelations":0.8106140948},{"Date":"30-01-2022","RollingCorrelations":0.8227175425},{"Date":"31-01-2022","RollingCorrelations":0.8780638086},{"Date":"01-02-2022","RollingCorrelations":0.8925733873},{"Date":"02-02-2022","RollingCorrelations":0.9077075104},{"Date":"03-02-2022","RollingCorrelations":0.9009935389},{"Date":"04-02-2022","RollingCorrelations":0.8709915309},{"Date":"05-02-2022","RollingCorrelations":0.8314422524},{"Date":"06-02-2022","RollingCorrelations":0.8520510323},{"Date":"07-02-2022","RollingCorrelations":0.8943370239},{"Date":"08-02-2022","RollingCorrelations":0.8797503881},{"Date":"09-02-2022","RollingCorrelations":0.891305124},{"Date":"10-02-2022","RollingCorrelations":0.8639699068},{"Date":"11-02-2022","RollingCorrelations":0.9101985837},{"Date":"12-02-2022","RollingCorrelations":0.9030803798},{"Date":"13-02-2022","RollingCorrelations":0.8516848059},{"Date":"14-02-2022","RollingCorrelations":0.8337396273},{"Date":"15-02-2022","RollingCorrelations":0.8305557835},{"Date":"16-02-2022","RollingCorrelations":0.8179500056},{"Date":"17-02-2022","RollingCorrelations":0.8649827063},{"Date":"18-02-2022","RollingCorrelations":0.7563473684},{"Date":"19-02-2022","RollingCorrelations":0.760457297},{"Date":"20-02-2022","RollingCorrelations":0.7594475481},{"Date":"21-02-2022","RollingCorrelations":0.7662491177},{"Date":"22-02-2022","RollingCorrelations":0.7980780969},{"Date":"23-02-2022","RollingCorrelations":0.7774930178},{"Date":"24-02-2022","RollingCorrelations":0.7893140229},{"Date":"25-02-2022","RollingCorrelations":0.6524189835},{"Date":"26-02-2022","RollingCorrelations":0.6531331598},{"Date":"27-02-2022","RollingCorrelations":0.7142036627},{"Date":"28-02-2022","RollingCorrelations":0.7777542281},{"Date":"01-03-2022","RollingCorrelations":0.7533024852},{"Date":"02-03-2022","RollingCorrelations":0.7592802763},{"Date":"03-03-2022","RollingCorrelations":0.7508237795},{"Date":"04-03-2022","RollingCorrelations":0.7969972417},{"Date":"05-03-2022","RollingCorrelations":0.7701400536},{"Date":"06-03-2022","RollingCorrelations":0.7818865795},{"Date":"07-03-2022","RollingCorrelations":0.7525076892},{"Date":"08-03-2022","RollingCorrelations":0.7055209647},{"Date":"09-03-2022","RollingCorrelations":0.6963515079},{"Date":"10-03-2022","RollingCorrelations":0.7103523697},{"Date":"11-03-2022","RollingCorrelations":0.8305104848},{"Date":"12-03-2022","RollingCorrelations":0.8272895413},{"Date":"13-03-2022","RollingCorrelations":0.8126964383},{"Date":"14-03-2022","RollingCorrelations":0.6684464933},{"Date":"15-03-2022","RollingCorrelations":0.6759846878},{"Date":"16-03-2022","RollingCorrelations":0.6501619137},{"Date":"17-03-2022","RollingCorrelations":0.4882667953},{"Date":"18-03-2022","RollingCorrelations":0.4569890119},{"Date":"19-03-2022","RollingCorrelations":0.527524437},{"Date":"20-03-2022","RollingCorrelations":0.449599349},{"Date":"21-03-2022","RollingCorrelations":0.4394114737},{"Date":"22-03-2022","RollingCorrelations":0.3167055755},{"Date":"23-03-2022","RollingCorrelations":0.339644594},{"Date":"24-03-2022","RollingCorrelations":0.192465962},{"Date":"25-03-2022","RollingCorrelations":0.3588380632},{"Date":"26-03-2022","RollingCorrelations":0.3519397197},{"Date":"27-03-2022","RollingCorrelations":0.3204684767},{"Date":"28-03-2022","RollingCorrelations":0.3435667754},{"Date":"29-03-2022","RollingCorrelations":0.3282646613},{"Date":"30-03-2022","RollingCorrelations":0.3327194116},{"Date":"31-03-2022","RollingCorrelations":0.4798715607},{"Date":"01-04-2022","RollingCorrelations":0.5396205309},{"Date":"02-04-2022","RollingCorrelations":0.6087044515},{"Date":"03-04-2022","RollingCorrelations":0.5374868615},{"Date":"04-04-2022","RollingCorrelations":0.6277554958},{"Date":"05-04-2022","RollingCorrelations":0.789818624},{"Date":"06-04-2022","RollingCorrelations":0.890514972},{"Date":"07-04-2022","RollingCorrelations":0.8664086691},{"Date":"08-04-2022","RollingCorrelations":0.8810759798},{"Date":"09-04-2022","RollingCorrelations":0.8716499934},{"Date":"10-04-2022","RollingCorrelations":0.8584151438},{"Date":"11-04-2022","RollingCorrelations":0.8883963072},{"Date":"12-04-2022","RollingCorrelations":0.9066903256},{"Date":"13-04-2022","RollingCorrelations":0.9191855525},{"Date":"14-04-2022","RollingCorrelations":0.9151241333},{"Date":"15-04-2022","RollingCorrelations":0.9100137781},{"Date":"16-04-2022","RollingCorrelations":0.9172917157},{"Date":"17-04-2022","RollingCorrelations":0.9240700288},{"Date":"18-04-2022","RollingCorrelations":0.931979667},{"Date":"19-04-2022","RollingCorrelations":0.9420945752},{"Date":"20-04-2022","RollingCorrelations":0.9345593926},{"Date":"21-04-2022","RollingCorrelations":0.4441125884},{"Date":"22-04-2022","RollingCorrelations":0.384125238},{"Date":"23-04-2022","RollingCorrelations":0.3723932208},{"Date":"24-04-2022","RollingCorrelations":0.3609191432},{"Date":"25-04-2022","RollingCorrelations":0.0913613682},{"Date":"26-04-2022","RollingCorrelations":0.2048601427},{"Date":"27-04-2022","RollingCorrelations":0.1813489104},{"Date":"28-04-2022","RollingCorrelations":0.129841789},{"Date":"29-04-2022","RollingCorrelations":0.1093113603},{"Date":"30-04-2022","RollingCorrelations":0.1373174292},{"Date":"01-05-2022","RollingCorrelations":0.2981747069},{"Date":"02-05-2022","RollingCorrelations":0.2141385587},{"Date":"03-05-2022","RollingCorrelations":0.1965261153},{"Date":"04-05-2022","RollingCorrelations":0.5328501021},{"Date":"05-05-2022","RollingCorrelations":0.7690132284},{"Date":"06-05-2022","RollingCorrelations":0.6848732121},{"Date":"07-05-2022","RollingCorrelations":0.6848564172},{"Date":"08-05-2022","RollingCorrelations":0.6552067756},{"Date":"09-05-2022","RollingCorrelations":0.7869229434},{"Date":"10-05-2022","RollingCorrelations":0.7755435783},{"Date":"11-05-2022","RollingCorrelations":0.6218887384},{"Date":"12-05-2022","RollingCorrelations":0.5688348873},{"Date":"13-05-2022","RollingCorrelations":0.5930751734},{"Date":"14-05-2022","RollingCorrelations":0.5546152336},{"Date":"15-05-2022","RollingCorrelations":0.5217262303},{"Date":"16-05-2022","RollingCorrelations":0.551040548},{"Date":"17-05-2022","RollingCorrelations":0.5584252825},{"Date":"18-05-2022","RollingCorrelations":0.4674369603},{"Date":"19-05-2022","RollingCorrelations":0.4607653664},{"Date":"20-05-2022","RollingCorrelations":0.5208471077},{"Date":"21-05-2022","RollingCorrelations":0.5409775609},{"Date":"22-05-2022","RollingCorrelations":0.5940379803},{"Date":"23-05-2022","RollingCorrelations":0.5094055498},{"Date":"24-05-2022","RollingCorrelations":0.4824543857},{"Date":"25-05-2022","RollingCorrelations":0.4749932261},{"Date":"26-05-2022","RollingCorrelations":0.6060845375},{"Date":"27-05-2022","RollingCorrelations":0.5741341293},{"Date":"28-05-2022","RollingCorrelations":0.624253771},{"Date":"29-05-2022","RollingCorrelations":0.6233775982},{"Date":"30-05-2022","RollingCorrelations":0.5853991685},{"Date":"31-05-2022","RollingCorrelations":0.5541003825},{"Date":"01-06-2022","RollingCorrelations":0.5308028233},{"Date":"02-06-2022","RollingCorrelations":0.5023735686},{"Date":"03-06-2022","RollingCorrelations":0.5253467564},{"Date":"04-06-2022","RollingCorrelations":0.4343312521},{"Date":"05-06-2022","RollingCorrelations":0.3571778328},{"Date":"06-06-2022","RollingCorrelations":0.2828610127},{"Date":"07-06-2022","RollingCorrelations":0.3063769504},{"Date":"08-06-2022","RollingCorrelations":0.5298784265},{"Date":"09-06-2022","RollingCorrelations":0.4211814489},{"Date":"10-06-2022","RollingCorrelations":0.4760347704},{"Date":"11-06-2022","RollingCorrelations":0.5667534463},{"Date":"12-06-2022","RollingCorrelations":0.4912457347},{"Date":"13-06-2022","RollingCorrelations":0.3073134115},{"Date":"14-06-2022","RollingCorrelations":0.1150646156},{"Date":"15-06-2022","RollingCorrelations":0.374418023},{"Date":"16-06-2022","RollingCorrelations":0.3871944575},{"Date":"17-06-2022","RollingCorrelations":0.3983570634},{"Date":"18-06-2022","RollingCorrelations":0.3733089626},{"Date":"19-06-2022","RollingCorrelations":0.3812477489},{"Date":"20-06-2022","RollingCorrelations":0.3735187836},{"Date":"21-06-2022","RollingCorrelations":0.3790440192},{"Date":"22-06-2022","RollingCorrelations":0.3814993376},{"Date":"23-06-2022","RollingCorrelations":0.3790488964},{"Date":"24-06-2022","RollingCorrelations":0.4158071606},{"Date":"25-06-2022","RollingCorrelations":0.4035251609},{"Date":"26-06-2022","RollingCorrelations":0.442539745},{"Date":"27-06-2022","RollingCorrelations":0.3154769459},{"Date":"28-06-2022","RollingCorrelations":0.5172012208},{"Date":"29-06-2022","RollingCorrelations":0.4585883351},{"Date":"30-06-2022","RollingCorrelations":0.2177951553},{"Date":"01-07-2022","RollingCorrelations":0.2172711772},{"Date":"02-07-2022","RollingCorrelations":0.2720618329},{"Date":"03-07-2022","RollingCorrelations":0.2771926022},{"Date":"04-07-2022","RollingCorrelations":0.3351159871},{"Date":"05-07-2022","RollingCorrelations":0.4986154667},{"Date":"06-07-2022","RollingCorrelations":0.3853730354},{"Date":"07-07-2022","RollingCorrelations":0.424450868},{"Date":"08-07-2022","RollingCorrelations":0.2205461884},{"Date":"09-07-2022","RollingCorrelations":0.3434907275},{"Date":"10-07-2022","RollingCorrelations":0.4149222674},{"Date":"11-07-2022","RollingCorrelations":0.6833815628},{"Date":"12-07-2022","RollingCorrelations":0.6599853167},{"Date":"13-07-2022","RollingCorrelations":0.6979656318},{"Date":"14-07-2022","RollingCorrelations":0.7108759113},{"Date":"15-07-2022","RollingCorrelations":0.741641701},{"Date":"16-07-2022","RollingCorrelations":0.7723277161},{"Date":"17-07-2022","RollingCorrelations":0.80685762},{"Date":"18-07-2022","RollingCorrelations":0.7974662233},{"Date":"19-07-2022","RollingCorrelations":0.819259883},{"Date":"20-07-2022","RollingCorrelations":0.8669669906},{"Date":"21-07-2022","RollingCorrelations":0.8616840411},{"Date":"22-07-2022","RollingCorrelations":0.8868439676},{"Date":"23-07-2022","RollingCorrelations":0.9037733397},{"Date":"24-07-2022","RollingCorrelations":0.912149646},{"Date":"25-07-2022","RollingCorrelations":0.9290879356},{"Date":"26-07-2022","RollingCorrelations":0.8598076346},{"Date":"27-07-2022","RollingCorrelations":0.8681580596},{"Date":"28-07-2022","RollingCorrelations":0.8665728792},{"Date":"29-07-2022","RollingCorrelations":0.8700369776},{"Date":"30-07-2022","RollingCorrelations":0.8576296561},{"Date":"31-07-2022","RollingCorrelations":0.8564548547},{"Date":"01-08-2022","RollingCorrelations":0.8729453665},{"Date":"02-08-2022","RollingCorrelations":0.8781879482},{"Date":"03-08-2022","RollingCorrelations":0.8610279978},{"Date":"04-08-2022","RollingCorrelations":0.8804258135},{"Date":"05-08-2022","RollingCorrelations":0.8638365959},{"Date":"06-08-2022","RollingCorrelations":0.7951120285},{"Date":"07-08-2022","RollingCorrelations":0.783548853},{"Date":"08-08-2022","RollingCorrelations":0.6125814131},{"Date":"09-08-2022","RollingCorrelations":0.7427883229},{"Date":"10-08-2022","RollingCorrelations":0.576814703},{"Date":"11-08-2022","RollingCorrelations":0.5438511072},{"Date":"12-08-2022","RollingCorrelations":0.5471543004},{"Date":"13-08-2022","RollingCorrelations":0.5601855731},{"Date":"14-08-2022","RollingCorrelations":0.4831362801},{"Date":"15-08-2022","RollingCorrelations":0.559095745},{"Date":"16-08-2022","RollingCorrelations":0.3738295809},{"Date":"17-08-2022","RollingCorrelations":0.5082134121},{"Date":"18-08-2022","RollingCorrelations":0.546588291},{"Date":"19-08-2022","RollingCorrelations":0.6275404925},{"Date":"20-08-2022","RollingCorrelations":0.6586271564},{"Date":"21-08-2022","RollingCorrelations":0.6799878521},{"Date":"22-08-2022","RollingCorrelations":0.6742866146},{"Date":"23-08-2022","RollingCorrelations":0.6976478034},{"Date":"24-08-2022","RollingCorrelations":0.613403769},{"Date":"25-08-2022","RollingCorrelations":0.6263007868},{"Date":"26-08-2022","RollingCorrelations":0.7713736538},{"Date":"27-08-2022","RollingCorrelations":0.7386988917},{"Date":"28-08-2022","RollingCorrelations":0.7486854046},{"Date":"29-08-2022","RollingCorrelations":0.8151507205},{"Date":"30-08-2022","RollingCorrelations":0.8304787967},{"Date":"31-08-2022","RollingCorrelations":0.8057334053},{"Date":"01-09-2022","RollingCorrelations":0.8019719085},{"Date":"02-09-2022","RollingCorrelations":0.7683501898},{"Date":"03-09-2022","RollingCorrelations":0.8047304939},{"Date":"04-09-2022","RollingCorrelations":0.8208999152},{"Date":"05-09-2022","RollingCorrelations":0.7832009359},{"Date":"06-09-2022","RollingCorrelations":0.8064176842},{"Date":"07-09-2022","RollingCorrelations":0.824724749},{"Date":"08-09-2022","RollingCorrelations":0.8117290924},{"Date":"09-09-2022","RollingCorrelations":0.7534069207},{"Date":"10-09-2022","RollingCorrelations":0.8155662706},{"Date":"11-09-2022","RollingCorrelations":0.8083239179},{"Date":"12-09-2022","RollingCorrelations":0.7325152504},{"Date":"13-09-2022","RollingCorrelations":0.8533305598},{"Date":"14-09-2022","RollingCorrelations":0.8550177316},{"Date":"15-09-2022","RollingCorrelations":0.83384692},{"Date":"16-09-2022","RollingCorrelations":0.8301877666},{"Date":"17-09-2022","RollingCorrelations":0.8381563264},{"Date":"18-09-2022","RollingCorrelations":0.8340658137},{"Date":"19-09-2022","RollingCorrelations":0.8199438762},{"Date":"20-09-2022","RollingCorrelations":0.8055979003},{"Date":"21-09-2022","RollingCorrelations":0.7822607871},{"Date":"22-09-2022","RollingCorrelations":0.8140380426},{"Date":"23-09-2022","RollingCorrelations":0.7845774819},{"Date":"24-09-2022","RollingCorrelations":0.8218316033},{"Date":"25-09-2022","RollingCorrelations":0.8325393307},{"Date":"26-09-2022","RollingCorrelations":0.8539424995},{"Date":"27-09-2022","RollingCorrelations":0.7662799355},{"Date":"28-09-2022","RollingCorrelations":0.7742369101},{"Date":"29-09-2022","RollingCorrelations":0.6935822607},{"Date":"30-09-2022","RollingCorrelations":0.6940010887},{"Date":"01-10-2022","RollingCorrelations":0.678478291},{"Date":"02-10-2022","RollingCorrelations":0.4419030232},{"Date":"03-10-2022","RollingCorrelations":0.6187772197},{"Date":"04-10-2022","RollingCorrelations":0.5788408914},{"Date":"05-10-2022","RollingCorrelations":0.5927800337},{"Date":"06-10-2022","RollingCorrelations":0.4216827524},{"Date":"07-10-2022","RollingCorrelations":0.440224323},{"Date":"08-10-2022","RollingCorrelations":0.3870783887},{"Date":"09-10-2022","RollingCorrelations":0.3716043292},{"Date":"10-10-2022","RollingCorrelations":0.3272097843},{"Date":"11-10-2022","RollingCorrelations":0.3543406857},{"Date":"12-10-2022","RollingCorrelations":0.3521622716},{"Date":"13-10-2022","RollingCorrelations":0.3552282512},{"Date":"14-10-2022","RollingCorrelations":0.2985757953},{"Date":"15-10-2022","RollingCorrelations":0.3082334622},{"Date":"16-10-2022","RollingCorrelations":0.3196327149},{"Date":"17-10-2022","RollingCorrelations":0.3628723061},{"Date":"18-10-2022","RollingCorrelations":0.3354977032},{"Date":"19-10-2022","RollingCorrelations":0.3266616729},{"Date":"20-10-2022","RollingCorrelations":0.3587009601},{"Date":"21-10-2022","RollingCorrelations":0.2591685213},{"Date":"22-10-2022","RollingCorrelations":0.2580997408},{"Date":"23-10-2022","RollingCorrelations":0.2525972168},{"Date":"24-10-2022","RollingCorrelations":0.3438256232},{"Date":"25-10-2022","RollingCorrelations":0.3895366448},{"Date":"26-10-2022","RollingCorrelations":0.4103563158},{"Date":"27-10-2022","RollingCorrelations":0.3898844712},{"Date":"28-10-2022","RollingCorrelations":0.5966234269},{"Date":"29-10-2022","RollingCorrelations":0.6049921957},{"Date":"30-10-2022","RollingCorrelations":0.586916138},{"Date":"31-10-2022","RollingCorrelations":0.5635104332},{"Date":"01-11-2022","RollingCorrelations":0.5704638363},{"Date":"02-11-2022","RollingCorrelations":0.6434886084},{"Date":"03-11-2022","RollingCorrelations":0.6573639161},{"Date":"04-11-2022","RollingCorrelations":0.7678750175},{"Date":"05-11-2022","RollingCorrelations":0.7670638296},{"Date":"06-11-2022","RollingCorrelations":0.7833153357},{"Date":"07-11-2022","RollingCorrelations":0.779916611},{"Date":"08-11-2022","RollingCorrelations":0.8621491869},{"Date":"09-11-2022","RollingCorrelations":0.9391393276},{"Date":"10-11-2022","RollingCorrelations":0.9580909861},{"Date":"11-11-2022","RollingCorrelations":0.9695135955},{"Date":"12-11-2022","RollingCorrelations":0.966204183},{"Date":"13-11-2022","RollingCorrelations":0.8515442347},{"Date":"14-11-2022","RollingCorrelations":0.846430773}]